irekua_filters/__init__.py
irekua_filters/base.py
irekua_filters/licences.py
irekua_filters/sites.py
irekua_filters/version.py
irekua_filters/annotations/__init__.py
irekua_filters/annotations/annotation_tools.py
irekua_filters/annotations/annotation_votes.py
irekua_filters/annotations/annotations.py
irekua_filters/data_collections/__init__.py
irekua_filters/data_collections/collection_devices.py
irekua_filters/data_collections/collection_licences.py
irekua_filters/data_collections/collection_sampling_events.py
irekua_filters/data_collections/collection_sites.py
irekua_filters/data_collections/collection_users.py
irekua_filters/data_collections/data_collections.py
irekua_filters/data_collections/metacollections.py
irekua_filters/devices/__init__.py
irekua_filters/devices/device_brands.py
irekua_filters/devices/devices.py
irekua_filters/devices/physical_devices.py
irekua_filters/items/__init__.py
irekua_filters/items/items.py
irekua_filters/items/secondary_items.py
irekua_filters/items/sources.py
irekua_filters/items/tags.py
irekua_filters/locale/es/LC_MESSAGES/django.mo
irekua_filters/locale/es/LC_MESSAGES/django.po
irekua_filters/object_types/__init__.py
irekua_filters/object_types/annotation_types.py
irekua_filters/object_types/device_types.py
irekua_filters/object_types/entailment_types.py
irekua_filters/object_types/event_types.py
irekua_filters/object_types/item_types.py
irekua_filters/object_types/licence_types.py
irekua_filters/object_types/site_types.py
irekua_filters/object_types/term_types.py
irekua_filters/object_types/data_collections/__init__.py
irekua_filters/object_types/data_collections/collection_device_types.py
irekua_filters/object_types/data_collections/collection_item_types.py
irekua_filters/object_types/data_collections/collection_roles.py
irekua_filters/object_types/data_collections/collection_types.py
irekua_filters/object_types/sampling_events/__init__.py
irekua_filters/object_types/sampling_events/sampling_event_type_devices.py
irekua_filters-0.1.2.dist-info/LICENCE
irekua_filters-0.1.2.dist-info/METADATA
irekua_filters-0.1.2.dist-info/WHEEL
irekua_filters-0.1.2.dist-info/top_level.txt
irekua_filters-0.1.2.dist-info/RECORD
